atools_whisper-1.2.0.dist-info/METADATA
atools_whisper-1.2.0.dist-info/WHEEL
atools_whisper-1.2.0.dist-info/entry_points.txt
atools_whisper/.DS_Store
atools_whisper/__init__.py
atools_whisper/cli.py
atools_whisper/whisper/__init__.py
atools_whisper/whisper/assets/download_alice.sh
atools_whisper/whisper/assets/gpt2.tiktoken
atools_whisper/whisper/assets/ls_test.flac
atools_whisper/whisper/assets/mel_filters.npz
atools_whisper/whisper/assets/multilingual.tiktoken
atools_whisper/whisper/audio.py
atools_whisper/whisper/decoding.py
atools_whisper/whisper/load_models.py
atools_whisper/whisper/timing.py
atools_whisper/whisper/tokenizer.py
atools_whisper/whisper/torch_whisper.py
atools_whisper/whisper/transcribe.py
atools_whisper/whisper/whisper.py
atools_whisper-1.2.0.dist-info/RECORD
